flake8_digit_separator/__init__.py
flake8_digit_separator/__version__.py
flake8_digit_separator/checker.py
flake8_digit_separator/classifiers/__init__.py
flake8_digit_separator/classifiers/base.py
flake8_digit_separator/classifiers/classifier_binary.py
flake8_digit_separator/classifiers/classifier_complex.py
flake8_digit_separator/classifiers/classifier_float.py
flake8_digit_separator/classifiers/classifier_hex.py
flake8_digit_separator/classifiers/classifier_int.py
flake8_digit_separator/classifiers/classifier_octal.py
flake8_digit_separator/classifiers/classifier_scientific.py
flake8_digit_separator/classifiers/registry.py
flake8_digit_separator/classifiers/types.py
flake8_digit_separator/error.py
flake8_digit_separator/fds_numbers/__init__.py
flake8_digit_separator/fds_numbers/base.py
flake8_digit_separator/fds_numbers/enums.py
flake8_digit_separator/fds_numbers/fds_numbers.py
flake8_digit_separator/fds_numbers/types.py
flake8_digit_separator/py.typed
flake8_digit_separator/rules/__init__.py
flake8_digit_separator/rules/base.py
flake8_digit_separator/rules/rules.py
flake8_digit_separator/types.py
flake8_digit_separator/validators/__init__.py
flake8_digit_separator/validators/base.py
flake8_digit_separator/validators/registry.py
flake8_digit_separator/validators/types.py
flake8_digit_separator/validators/validator_binary.py
flake8_digit_separator/validators/validator_float.py
flake8_digit_separator/validators/validator_hex.py
flake8_digit_separator/validators/validator_int.py
flake8_digit_separator/validators/validator_octal.py
flake8_digit_separator-1.0.2.dist-info/LICENSE
flake8_digit_separator-1.0.2.dist-info/METADATA
flake8_digit_separator-1.0.2.dist-info/WHEEL
flake8_digit_separator-1.0.2.dist-info/entry_points.txt
flake8_digit_separator-1.0.2.dist-info/RECORD
