Metadata-Version: 2.3
Name: flake8-digit-separator
Version: 1.0.2
Summary: Correct placement of separators
License: MIT
Keywords: flake8,linter,PEP515,separator,code-style,python-linter,linting,code-standards,code-quality,flake8-plugin,flake8-formatter,code-checker,numbers,digits,FDS,Underscores,Numeric Literals
Author: Timur Valiev
Author-email: cptchunk@yandex.ru
Requires-Python: >=3.10,<4.0
Classifier: Development Status :: 5 - Production/Stable
Classifier: Framework :: Flake8
Classifier: Intended Audience :: Developers
Classifier: License :: OSI Approved :: MIT License
Classifier: Programming Language :: Python :: 3
Classifier: Programming Language :: Python :: 3.10
Classifier: Programming Language :: Python :: 3.11
Classifier: Programming Language :: Python :: 3.12
Classifier: Programming Language :: Python :: 3.13
Classifier: Programming Language :: Python :: 3.14
Classifier: Topic :: Software Development :: Libraries :: Python Modules
Classifier: Typing :: Typed
Requires-Dist: flake8 (>=7.1,<8.0)
Project-URL: Homepage, https://github.com/imtoopunkforyou/flake8-digit-separator
